skada/__init__.py
skada/_mapping.py
skada/_ot.py
skada/_pipeline.py
skada/_reweight.py
skada/_self_labeling.py
skada/_subspace.py
skada/_utils.py
skada/base.py
skada/metrics.py
skada/model_selection.py
skada/transformers.py
skada/utils.py
skada/version.py
skada/datasets/__init__.py
skada/datasets/_amazon_review.py
skada/datasets/_base.py
skada/datasets/_mnist_usps.py
skada/datasets/_office.py
skada/datasets/_office_home.py
skada/datasets/_samples_generator.py
skada/datasets/tests/test_amazon_review.py
skada/datasets/tests/test_base_dataset.py
skada/datasets/tests/test_mnist_usps.py
skada/datasets/tests/test_office.py
skada/datasets/tests/test_office_home.py
skada/datasets/tests/test_samples_generator.py
skada/deep/__init__.py
skada/deep/_adversarial.py
skada/deep/_baseline.py
skada/deep/_class_confusion.py
skada/deep/_divergence.py
skada/deep/_graph_alignment.py
skada/deep/_optimal_transport.py
skada/deep/base.py
skada/deep/callbacks.py
skada/deep/losses.py
skada/deep/modules.py
skada/deep/utils.py
skada/deep/tests/test_deep_adversarial.py
skada/deep/tests/test_deep_base.py
skada/deep/tests/test_deep_baseline.py
skada/deep/tests/test_deep_class_confusion.py
skada/deep/tests/test_deep_dadataset.py
skada/deep/tests/test_deep_divergence.py
skada/deep/tests/test_deep_graph_alignment.py
skada/deep/tests/test_deep_module.py
skada/deep/tests/test_deep_optimal_transport.py
skada/deep/tests/test_deep_pipeline.py
skada/deep/tests/test_deep_scorer.py
skada/deep/tests/test_deep_utils.py
skada/tests/test_base.py
skada/tests/test_cv.py
skada/tests/test_label_prop.py
skada/tests/test_mapping.py
skada/tests/test_ot.py
skada/tests/test_pipeline.py
skada/tests/test_reweight.py
skada/tests/test_scorer.py
skada/tests/test_selector.py
skada/tests/test_self_labeling.py
skada/tests/test_subspace.py
skada/tests/test_transformers.py
skada/tests/test_utils.py
skada-0.5.0.dist-info/licenses/COPYING
skada-0.5.0.dist-info/METADATA
skada-0.5.0.dist-info/WHEEL
skada-0.5.0.dist-info/top_level.txt
skada-0.5.0.dist-info/RECORD
