Metadata-Version: 2.4
Name: skada
Version: 0.5.0
Summary: A Python package for domain adaptation compatible with scikit-learn and Pytorch.
Author: SKADA Team
License: BSD 3-Clause License
Project-URL: homepage, https://scikit-adaptation.github.io/
Project-URL: documentation, https://scikit-adaptation.github.io/
Project-URL: repository, https://github.com/scikit-adaptation/skada/
Keywords: domain-adaptation,scikit-learn,pytorch,machine learning,deep learning
Classifier: Intended Audience :: Science/Research
Classifier: Intended Audience :: Developers
Classifier: License :: OSI Approved :: BSD License
Classifier: Programming Language :: C
Classifier: Programming Language :: Python
Classifier: Topic :: Software Development
Classifier: Topic :: Scientific/Engineering
Classifier: Development Status :: 3 - Alpha
Classifier: Operating System :: Microsoft :: Windows
Classifier: Operating System :: POSIX
Classifier: Operating System :: Unix
Classifier: Operating System :: MacOS
Classifier: Programming Language :: Python :: 3
Classifier: Programming Language :: Python :: 3.9
Classifier: Programming Language :: Python :: 3.10
Classifier: Programming Language :: Python :: 3.11
Classifier: Programming Language :: Python :: 3.12
Requires-Python: >=3.9
License-File: COPYING
Requires-Dist: numpy>=1.24
Requires-Dist: scipy>=1.10
Requires-Dist: scikit-learn>=1.5.0
Requires-Dist: POT>=0.9.3
Requires-Dist: pandas>=2.3.0
Provides-Extra: subspace
Requires-Dist: torch; extra == "subspace"
Provides-Extra: deep
Requires-Dist: torch; extra == "deep"
Requires-Dist: torchvision; extra == "deep"
Requires-Dist: skorch; extra == "deep"
Provides-Extra: test
Requires-Dist: pytest; extra == "test"
Requires-Dist: pytest-cov; extra == "test"
Requires-Dist: codecov; extra == "test"
Provides-Extra: doc
Requires-Dist: sphinx; extra == "doc"
Requires-Dist: sphinx_gallery; extra == "doc"
Requires-Dist: sphinx_rtd_theme; extra == "doc"
Requires-Dist: numpydoc; extra == "doc"
Requires-Dist: memory_profiler; extra == "doc"
Requires-Dist: myst-parser; extra == "doc"
Requires-Dist: ipython; extra == "doc"
Requires-Dist: matplotlib; extra == "doc"
Requires-Dist: torch; extra == "doc"
Requires-Dist: torchvision; extra == "doc"
Requires-Dist: skorch; extra == "doc"
Dynamic: license-file
